nomad_camels_driver_andor_shamrock_500/__init__.py
nomad_camels_driver_andor_shamrock_500/andor_shamrock_500.py
nomad_camels_driver_andor_shamrock_500/andor_shamrock_500_config.py
nomad_camels_driver_andor_shamrock_500/andor_shamrock_500_config_sub.py
nomad_camels_driver_andor_shamrock_500/andor_shamrock_500_manual_control.py
nomad_camels_driver_andor_shamrock_500/andor_shamrock_500_ophyd.py
nomad_camels_driver_andor_shamrock_500-0.1.4.dist-info/licenses/LICENSE.txt
nomad_camels_driver_andor_shamrock_500-0.1.4.dist-info/METADATA
nomad_camels_driver_andor_shamrock_500-0.1.4.dist-info/WHEEL
nomad_camels_driver_andor_shamrock_500-0.1.4.dist-info/top_level.txt
nomad_camels_driver_andor_shamrock_500-0.1.4.dist-info/RECORD
